KratosMultiphysics/MPMApplication/__init__.py
KratosMultiphysics/MPMApplication/apply_mpm_3d_rotating_dirichlet_condition_process.py
KratosMultiphysics/MPMApplication/apply_mpm_coupling_interface_dirichlet_condition_process.py
KratosMultiphysics/MPMApplication/apply_mpm_coupling_interface_neumann_condition_process.py
KratosMultiphysics/MPMApplication/apply_mpm_particle_dirichlet_condition_process.py
KratosMultiphysics/MPMApplication/apply_mpm_particle_neumann_condition_process.py
KratosMultiphysics/MPMApplication/apply_mpm_slip_boundary_process.py
KratosMultiphysics/MPMApplication/assign_gravity_to_material_point_process.py
KratosMultiphysics/MPMApplication/assign_gravity_to_particle_process.py
KratosMultiphysics/MPMApplication/assign_initial_velocity_to_material_point_process.py
KratosMultiphysics/MPMApplication/assign_initial_velocity_to_particle_process.py
KratosMultiphysics/MPMApplication/kratos_main_mpm.py
KratosMultiphysics/MPMApplication/mpm_analysis.py
KratosMultiphysics/MPMApplication/mpm_explicit_solver.py
KratosMultiphysics/MPMApplication/mpm_from_json_check_result_process.py
KratosMultiphysics/MPMApplication/mpm_gid_output_process.py
KratosMultiphysics/MPMApplication/mpm_implicit_dynamic_solver.py
KratosMultiphysics/MPMApplication/mpm_json_output_process.py
KratosMultiphysics/MPMApplication/mpm_quasi_static_solver.py
KratosMultiphysics/MPMApplication/mpm_solver.py
KratosMultiphysics/MPMApplication/mpm_static_solver.py
KratosMultiphysics/MPMApplication/mpm_vtk_output_process.py
KratosMultiphysics/MPMApplication/particle_from_json_check_result_process.py
KratosMultiphysics/MPMApplication/particle_gid_output_process.py
KratosMultiphysics/MPMApplication/particle_json_output_process.py
KratosMultiphysics/MPMApplication/particle_mechanics_analysis.py
KratosMultiphysics/MPMApplication/particle_vtk_output_process.py
KratosMultiphysics/MPMApplication/python_solvers_wrapper_mpm.py
KratosMultiphysics/.libs/KratosMPMApplication.cpython-39-x86_64-linux-gnu.so
kratosmpmapplication-10.4.0.dist-info/METADATA
kratosmpmapplication-10.4.0.dist-info/WHEEL
kratosmpmapplication-10.4.0.dist-info/RECORD
